{
  "ontologies": [
    {
      "id": "ohdab",
      "preferredPrefix":"OhdAB",
      "title":"Ontology of the historical German-language nomenclature for offices and professions | OhdAB",
      "uri": "https://database.factgrid.de/ohdab",
      "description":"This version of the historical German-language nomenclature for offices and professions (OhdAB) was automatically generated via a script from FactGrid.",
      "homepage":"https://database.factgrid.de",
      "hierarchical_property": [
          "https://w3id.org/omw/broader"
      ],
      "base_uri": [
          "https://database.factgrid.de"
      ],
      "ontology_purl": "https://raw.githubusercontent.com/ts4nfdi/Wikibase-ts-convert/refs/heads/main/OhdAB.ttl"
    }
  ]
}
